rushrunning/__init__.py
rushrunning-0.1.2.dist-info/licenses/LICENSE.txt
scripts/build.py
scripts/install.py
rushrunning-0.1.2.dist-info/METADATA
rushrunning-0.1.2.dist-info/WHEEL
rushrunning-0.1.2.dist-info/top_level.txt
rushrunning-0.1.2.dist-info/RECORD
