Metadata-Version: 2.4
Name: rushrunning
Version: 0.1.2
Summary: python lib
Author-email: ndrzy <dandan0019@outlook.com>
License: MIT
Project-URL: Homepage, https://github.com/meatdumplings0019/rushrunning
Requires-Python: >=3.10
License-File: LICENSE.txt
Requires-Dist: rushlib
Dynamic: license-file
